poro/__init__.py
poro/data.py
poro/poro.py
poro/utils.py
poro/_configuration/__init__.py
poro/_configuration/pipeline.py
poro/apis/__init__.py
poro/apis/common.py
poro/apis/ddragon/__init__.py
poro/apis/ddragon/champion.py
poro/apis/ddragon/item.py
poro/apis/ddragon/perk.py
poro/apis/ddragon/profileicon.py
poro/apis/ddragon/spell.py
poro/apis/ddragon/sprite.py
poro/apis/ddragon/version.py
poro/apis/riotapi/__init__.py
poro/apis/riotapi/match.py
poro/apis/riotapi/summoner.py
poro/core/__init__.py
poro/core/common.py
poro/core/ddragon/__init__.py
poro/core/ddragon/champion.py
poro/core/ddragon/item.py
poro/core/ddragon/perk.py
poro/core/ddragon/profileicon.py
poro/core/ddragon/spell.py
poro/core/ddragon/sprite.py
poro/core/ddragon/version.py
poro/core/riotapi/__init__.py
poro/core/riotapi/match.py
poro/core/riotapi/summoner.py
poro/dto/__init__.py
poro/dto/common.py
poro/dto/ddragon/__init__.py
poro/dto/ddragon/champion.py
poro/dto/ddragon/item.py
poro/dto/ddragon/perk.py
poro/dto/ddragon/profileicon.py
poro/dto/ddragon/spell.py
poro/dto/ddragon/sprite.py
poro/dto/ddragon/version.py
poro/dto/riotapi/__init__.py
poro/dto/riotapi/match.py
poro/dto/riotapi/summoner.py
poro/transformers/__init__.py
poro/transformers/ddragon/__init__.py
poro/transformers/ddragon/champion.py
poro/transformers/ddragon/item.py
poro/transformers/ddragon/perk.py
poro/transformers/ddragon/profileicon.py
poro/transformers/ddragon/spell.py
poro/transformers/ddragon/sprite.py
poro/transformers/ddragon/version.py
poro/transformers/riotapi/__init__.py
poro/transformers/riotapi/match.py
poro/transformers/riotapi/summoner.py
aramgg_poro-0.0.8.dist-info/LICENSE.txt
aramgg_poro-0.0.8.dist-info/METADATA
aramgg_poro-0.0.8.dist-info/WHEEL
aramgg_poro-0.0.8.dist-info/top_level.txt
aramgg_poro-0.0.8.dist-info/RECORD
