Metadata-Version: 2.1
Name: aramgg-poro
Version: 0.0.8
Summary: aramgg riotapi lib
Home-page: https://github.com/poro/
Author: peep12ng
Author-email: peep12ng@gmail.com
Project-URL: Bug Tracker, https://github.com/poro/issues
Classifier: Programming Language :: Python :: 3
Classifier: License :: OSI Approved :: MIT License
Classifier: Operating System :: OS Independent
Requires-Python: >=3.6
License-File: LICENSE.txt
Requires-Dist: setuptools (>=42)
Requires-Dist: Pillow
Requires-Dist: requests
